md2api/run.py
md2api-0.5.1.dist-info/LICENSE
md2api-0.5.1.dist-info/METADATA
md2api-0.5.1.dist-info/WHEEL
md2api-0.5.1.dist-info/entry_points.txt
md2api-0.5.1.dist-info/RECORD
